rcute_cozmars_server/__init__.py
rcute_cozmars_server/__main__.py
rcute_cozmars_server/cozmars_server.py
rcute_cozmars_server/distance_sensor.py
rcute_cozmars_server/rcute_servokit.py
rcute_cozmars_server/save_wifi.sh
rcute_cozmars_server/util.py
rcute_cozmars_server/version.py
rcute_cozmars_server/locales/base.pot
rcute_cozmars_server/locales/zh/LC_MESSAGES/base.mo
rcute_cozmars_server/locales/zh/LC_MESSAGES/base.po
rcute_cozmars_server/static/DejaVuSans.ttf
rcute_cozmars_server/static/__init__.py
rcute_cozmars_server/static/cozmars.js
rcute_cozmars_server/static/index.html
rcute_cozmars_server/static/motor.html
rcute_cozmars_server/static/msgpack.min.js
rcute_cozmars_server/static/poweroff.png
rcute_cozmars_server/static/reboot.png
rcute_cozmars_server/static/servo.html
rcute_cozmars_server/static/sine_800hz_16k_i8.raw
rcute_cozmars_server/static/test.html
rcute_cozmars_server/static/wifi.html
rcute_cozmars_server/static/wsmprpc.client.js
rcute_cozmars_server-2.0.1.dist-info/DESCRIPTION.rst
rcute_cozmars_server-2.0.1.dist-info/METADATA
rcute_cozmars_server-2.0.1.dist-info/RECORD
rcute_cozmars_server-2.0.1.dist-info/WHEEL
rcute_cozmars_server-2.0.1.dist-info/metadata.json
rcute_cozmars_server-2.0.1.dist-info/top_level.txt
