Metadata-Version: 2.0
Name: rcute-cozmars-server
Version: 2.0.1
Summary: R-Cute 教育机器人 Cozmars 固件
Home-page: https://github.com/hyansuper/rcute-cozmars-server
Author: Huang Yan
Author-email: hyansuper@foxmail.com
License: Non-Commercial
Platform: UNKNOWN
Classifier: Programming Language :: Python :: 3.7
Classifier: Operating System :: OS Independent
Requires-Dist: Pillow
Requires-Dist: adafruit-circuitpython-rgb-display
Requires-Dist: adafruit-circuitpython-servokit
Requires-Dist: gpiozero
Requires-Dist: picamera
Requires-Dist: sanic
Requires-Dist: sounddevice
Requires-Dist: wsmprpc (>=1.1.2)
